ladybug_geometry_polyskel/__init__.py
ladybug_geometry_polyskel/__main__.py
ladybug_geometry_polyskel/offset.py
ladybug_geometry_polyskel/polygraph.py
ladybug_geometry_polyskel/polyskel.py
ladybug_geometry_polyskel/polysplit.py
ladybug_geometry_polyskel/cli/__init__.py
ladybug_geometry_polyskel-1.7.37.dist-info/licenses/LICENSE
ladybug_geometry_polyskel-1.7.37.dist-info/METADATA
ladybug_geometry_polyskel-1.7.37.dist-info/WHEEL
ladybug_geometry_polyskel-1.7.37.dist-info/entry_points.txt
ladybug_geometry_polyskel-1.7.37.dist-info/top_level.txt
ladybug_geometry_polyskel-1.7.37.dist-info/RECORD
